{
    "title": "《孙昌武文集》出版暨孙昌武学术研究座谈会在京召开-南开要闻-南开大学",
    "url": "https://news.nankai.edu.cn/ywsd/system/2024/12/05/030064915.shtml",
    "publish_time": "2024-12-05",
    "content": "首页\n南开要闻\n媒体南开\n南开校史\n光影南开\n南开故事\n南开大学报\n视频\n广播\n您当前的位置 ：\n南开大学\n>>\n南开要闻\n《孙昌武文集》出版暨孙昌武学术研究座谈会在京召开\n发稿 20:14\n南开新闻网讯\n（通讯员 张培锋 李志明）南开大学文学院教授孙昌武先生的全部著作和论文，近几年经过重新审阅、编辑、校订，最终编纂为共计三十卷的《孙昌武文集》，由中华书局陆续结集出版。12月3日，由南开大学、中华书局、北京横山书院共同主办的《孙昌武文集》出版暨孙昌武学术研究座谈会在京召开。\n南开大学党委常务副书记杨克欣、中华书局总编辑尹涛编审、北京横山书院湛如教授出席并分别代表主办单位致辞。来自北京大学、中国社会科学院、南开大学、武汉大学、浙江师范大学、天津师范大学、敦煌研究院、中华书局、天津人民出版社等单位的专家学者，以及南开大学人文社会科学研究部、文学院负责人参加会议。\n杨克欣在致辞中指出，孙昌武先生的学术研究兼顾文学、历史学、哲学、宗教学等多个学科，融会贯通，形成了独特的研究方法与学术范式，为构建中国自主知识体系的新时代哲学社会科学做出了重大贡献，其经验值得认真总结、学习弘扬。\n尹涛回顾了《孙昌武文集》的策划、出版过程。他说，孙先生在多年的学术生涯中，与中华书局建立了深厚的友谊，在当代学者相关领域的研究中，孙先生堪称用力最勤、功夫最深，而本次整理出版的三十卷巨著，包含了孙先生大部分学术成果。\n湛如说，本次能将孙先生数十年来的学术心血系统的予以整理出版，过程殊为不易，先生的著作不仅具有学术意义，对于建立中华民族共同体亦具有现实意义，先生的学术实践对于如何讲好中国故事，将中国知识分子的原创性成果推介向全世界，具有重要的参考价值。\n孙昌武向多年来支持他学术研究的单位和个人表达了感激之情。他表示，正是中华书局多年来对自己学术事业的关注，南开大学在学术和生活上对自己的照顾，湛如教授对自己的全面支持，以及学界同仁的帮助关照，文集才得以顺利出版。孙先生的致辞感人非常，与会专家学者无不动容。\n三家主办单位领导为《孙昌武文集》揭幕。简短而隆重的揭幕仪式后，与会学者围绕孙昌武先生的学术成就、学术精神、学术理念和学术影响等进行了热烈讨论和深入阐发。\n中国社会科学院学部委员、文学研究所刘跃进研究员，中国社会科学院世界宗教研究所黄夏年研究员，南开大学宁稼雨教授，天津师范大学王晓平教授，浙江师范大学张弘教授，武汉大学吴光正教授，敦煌研究院王志鹏研究员，中国外文出版发行事业局\n原\n副局长方正辉，中国社会科学院文学研究所编审祝晓风，天津人民出版社副总编辑王轶冰，天津教育出版社编审李勃洋等专家学者在发言中高度评价了孙昌武先生的学术成就。大家一致认为，孙昌武先生是国内外公认的当代佛教文学研究领域的领军人物，他的很多著作已经成为本学科领域的学术经典，在国内外学术界享有盛誉，对中国古代文学特别是宗教文学的研究产生了重要影响。《孙昌武文集》汇集了孙昌武教授重要的学术成果，它的出版必将对中国古代文学学科建设以及中国宗教文学研究的深化发挥积极作用。\n《孙昌武文集》收录孙昌武先生已出版专著、论文集；另增加未曾出版的专著《文苑杂谈》《解说观音》《僧诗与诗僧》三种；孙先生在国内外学术刊物发表的论文未曾辑入论文集的，另编为若干集收入。孙先生整理的古籍、翻译的外国学者著作，不包括在本文集内。中华书局编辑部对文字重新进行了审核、校订，旨在希望以此为孙先生著作定本呈献给读者。\n编辑：\n韦承金\n微信往期推送\n更多...\n西南联合研究生院博士生学术...\n南开大学召开智库建设重点工...\n重磅签约！南开大学第一附属...\n缅怀大师！南开大学首颁数学...\n我校牵头国家自然科学基金重...\n2024数字创意驱动城市高质量...\n南开数项智库成果获评CTTI智...\n“超越传统的电池体系”重大...\n先进能源材料化学教育部重点...\neScience卓越讲座和研究生线...\n新闻热线：022-23508464 022-85358737\n投稿信箱：\n本网站由南开大学新闻中心设计维护\nCopyright@2014 津ICP备12003308号-1\n南开大学\n校史网\n版权声明：本网站由南开大学版权所有，如转载本网站内容，请注明出处。",
    "images": [
        "http://news.nankai.edu.cn/images/i_weixin.png",
        "http://news.nankai.edu.cn/images/weixin.jpg",
        "http://news.nankai.edu.cn/images/i_weibo.png",
        "http://news.nankai.edu.cn/images/weibo.jpg",
        "http://news.nankai.edu.cn/images/i_douyin.png",
        "http://news.nankai.edu.cn/images/dy11.png",
        "http://news.nankai.edu.cn/images/i_blibili.png",
        "http://news.nankai.edu.cn/images/bz.png",
        "http://news.nankai.edu.cn/images/kuaishou.png",
        "http://news.nankai.edu.cn/images/kuaishou1.png",
        "http://news.nankai.edu.cn/images/xxqg.png",
        "http://news.nankai.edu.cn/images/xxqgewm.png",
        "http://news.nankai.edu.cn/images/ys.png",
        "http://news.nankai.edu.cn/images/yangshipin1.png",
        "http://news.nankai.edu.cn/images/jiaoyu.png",
        "http://news.nankai.edu.cn/images/jybewm.png",
        "http://news.nankai.edu.cn/images/toutiao.png",
        "http://news.nankai.edu.cn/images/toutiaohao1.png",
        "http://news.nankai.edu.cn/pic/003/000/719/00300071947_a39e30a7.png",
        "http://news.nankai.edu.cn/pic/003/000/719/00300071948_e8de45b4.png",
        "http://news.nankai.edu.cn/pic/003/000/719/00300071949_94872f98.png",
        "http://news.nankai.edu.cn/pic/003/000/719/00300071952_38569cb0.png",
        "http://news.nankai.edu.cn/pic/003/000/719/00300071951_c229a37e.png",
        "http://news.nankai.edu.cn/pic/003/000/719/00300071953_9be2f686.png",
        "http://news.nankai.edu.cn/pic/003/000/719/00300071954_573ddc08.png",
        "http://news.nankai.edu.cn/pic/003/000/719/00300071955_39b905c0.png",
        "http://news.nankai.edu.cn/ywsd/images/list_04.jpg",
        "http://news.nankai.edu.cn/ywsd/images/list_12.jpg",
        "http://news.nankai.edu.cn/pic/003/000/241/00300024169_6a089d05.jpg",
        "http://news.nankai.edu.cn/ywsd/images/list_21.jpg"
    ],
    "links": [
        "http://news.nankai.edu.cn/index.shtml",
        "http://news.nankai.edu.cn/ywsd/index.shtml",
        "http://news.nankai.edu.cn/mtnk/index.shtml",
        "http://news.nankai.edu.cn/gynk/index.shtml",
        "http://news.nankai.edu.cn/nkrw/index.shtml",
        "http://news.nankai.edu.cn/nkdxb/index.shtml",
        "http://news.nankai.edu.cn/sp/index.shtml",
        "http://news.nankai.edu.cn/gb/index.shtml",
        "http://news.nankai.edu.cn/index.shtml",
        "http://news.nankai.edu.cn/ywsd/index.shtml",
        "http://news.nankai.edu.cn/wx/system/2019/06/03/030033750.shtml",
        "http://news.nankai.edu.cn/wx/system/2019/06/03/030033750.shtml",
        "http://news.nankai.edu.cn/wx/index.shtml",
        "http://news.nankai.edu.cn/ywsd/system/2024/12/03/030064867.shtml",
        "http://news.nankai.edu.cn/ywsd/system/2024/12/05/030064916.shtml",
        "http://news.nankai.edu.cn/ywsd/system/2024/12/05/030064905.shtml",
        "http://news.nankai.edu.cn/ywsd/system/2024/12/04/030064892.shtml",
        "http://news.nankai.edu.cn/ywsd/system/2024/12/05/030064917.shtml",
        "http://news.nankai.edu.cn/ywsd/system/2024/12/03/030064855.shtml",
        "http://news.nankai.edu.cn/ywsd/system/2024/12/05/030064914.shtml",
        "http://news.nankai.edu.cn/ywsd/system/2024/12/05/030064912.shtml",
        "http://news.nankai.edu.cn/ywsd/system/2024/12/04/030064885.shtml",
        "http://news.nankai.edu.cn/ywsd/system/2024/12/03/030064868.shtml"
    ],
    "publisher": "未知",
    "source": "南开大学新闻网",
    "views": null,
    "attachments": [],
    "contact_info": {
        "email": "nknews@nankai.edu.cn"
    }
}