{
    "title": "【党纪学习教育】金融学院把好“四关” 多措并举让党纪学习教育入脑入心-综合新闻-南开大学",
    "url": "https://news.nankai.edu.cn/zhxw/system/2024/05/20/030061696.shtml",
    "publish_time": "2024-05-20",
    "content": "首页\n南开要闻\n媒体南开\n南开校史\n光影南开\n南开故事\n南开大学报\n视频\n广播\n您当前的位置 ：\n南开大学\n>>\n综合新闻\n【党纪学习教育】金融学院把好“四关” 多措并举让党纪学习教育入脑入心\n发稿 17:33\n南开新闻网讯\n（通讯员 李佳音)金融学院深入贯彻习近平总书记关于开展党纪学习教育的重要讲话和重要指示精神，深刻理解和把握《中国共产党纪律处分条例》的内涵和要求，聚焦“入口关”“发展关”“培养关”“出口关”开展系列活动，将党纪学习教育融入日常、抓在经常，引导广大党员同志学纪、知纪、明纪、守纪，并辐射带动全院学子入脑入心。\n把牢“入口关”，加强理论武装\n组织多场主题学习。5月以来，通过个人自学与集中学习相结合的形式，组织全院16个学生党支部、共计404名党员充分利用“三会一课”、学习强国APP等载体逐章逐条学习，全面熟悉各项纪律要求；依托第九期“寻铸”入党积极分子培训班，结合等特色方式，面向新一批发展对象、入党积极分子180名学生开展交流研讨、案例阐释、主题学习等，进一步提高学生们的理论素养和辨识能力。\n组织一次书籍推介。近日，学院依托“书香金融”品牌活动，为各支部发放《习近平总书记关于金融工作的论述摘编》一书，将党纪学习教育与学习贯彻习近平总书记关于培育中国金融文化的重要论述相结合，并动员学生党员面向全院推荐廉政主题的红色书籍，在支部内进行交流分享和宣传推广。\n把牢“培养关”，加强思想引领\n开展多期骨干培训。为持续推动党支部标准化规范化建设，巩固学生党支部骨干力量，结合学校相关部署，金融学院组织党员骨干参加校级、院级主题培训。5月20日，学院组织召开“廉润初心，聚力赋能”学生党员骨干能力提升研讨会，学院党委副书记高珊为大家详细梳理党纪学习教育的可实施路径，就党建工作困境解疑纾困；专职组织员姜斯琪就“三会一课”常态化工作进行督促和指导，提升大家的工作热情和工作效率，进一步凝聚共识、增强认同。\n组织一场集体观影。学院坚持以娱促学、以学促思、以思促践，于5月初组织新一批发展对象集体观看党纪学习教育片《领航》并在观影后进行分组讨论，通过回首党的十年非凡历程，引导广大金融学子正确处理义和利的关系，进一步增强历史自信和历史主动。\n把牢“发展关”，加强本领赋能\n组织一次实践研学。聚焦廉政文化建设，学院拟组织百名学生于5月底赴天津市廉政教育基地——廉润初心文化传播推广中心进行实地研学。引导广大学子在中华优秀传统文化、红色革命文化、天津市市民文化的浸润下，加强党性修养，提高政治站位，使认同、追随、践行的种子深植在金融学子心中。\n举办一场知识竞赛。为加大党纪学习教育的宣传力度，结合学校“清廉南开润初心，牢记嘱托育英才”主题知识竞赛的相关要求，将辐射范围扩大至全体学生党员，组织大家认真学习《中国共产党章程》《中国共产党纪律处分条例》、中国特色金融文化等并积极组织参赛，在以赛促学、以学促用的过程中进一步激发学习热情，巩固党纪学习教育成果。\n把牢“出口关”，恪守身份初心\n开展廉洁教育“最后一课”。为引导本硕博毕业生党员切实增强党性修养，牢记初心使命，充分发挥党员的先锋模范作用，以饱满的青春热情、良好的精神风貌踏入人生新征程，在毕业季来临之际，学院组织毕业党员集中学习习近平总书记关于党风廉政建设、廉洁文化建设的重要论述，开展“以义取利，恪守初心”毕业季主题党日，以“最后一课”的形式号召大家保持勤奋清廉，守住人生底线，永葆公能本色。\n金融学院将切实把好四关，将学习教育对象精细化分类、学习教育内容精准化匹配，结合学院实际，依托不同学生群体的差异化诉求和现实侧重点分层分类开展党纪学习教育，切实将学习具体成效转化为做好“金融五篇大文章”的实际成效和推动金融学院高质量发展的强大动力。\n编辑：\n闫瑾\n微信往期推送\n更多...\n西南联合研究生院博士生学术...\n南开大学召开智库建设重点工...\n重磅签约！南开大学第一附属...\n缅怀大师！南开大学首颁数学...\n我校牵头国家自然科学基金重...\n2024数字创意驱动城市高质量...\n南开数项智库成果获评CTTI智...\n“超越传统的电池体系”重大...\n先进能源材料化学教育部重点...\neScience卓越讲座和研究生线...\n新闻热线：022-23508464 022-85358737\n投稿信箱：\n本网站由南开大学新闻中心设计维护\nCopyright@2014 津ICP备12003308号-1\n南开大学\n校史网\n版权声明：本网站由南开大学版权所有，如转载本网站内容，请注明出处。",
    "images": [
        "http://news.nankai.edu.cn/images/i_weixin.png",
        "http://news.nankai.edu.cn/images/weixin.jpg",
        "http://news.nankai.edu.cn/images/i_weibo.png",
        "http://news.nankai.edu.cn/images/weibo.jpg",
        "http://news.nankai.edu.cn/images/i_douyin.png",
        "http://news.nankai.edu.cn/images/dy11.png",
        "http://news.nankai.edu.cn/images/i_blibili.png",
        "http://news.nankai.edu.cn/images/bz.png",
        "http://news.nankai.edu.cn/images/kuaishou.png",
        "http://news.nankai.edu.cn/images/kuaishou1.png",
        "http://news.nankai.edu.cn/images/xxqg.png",
        "http://news.nankai.edu.cn/images/xxqgewm.png",
        "http://news.nankai.edu.cn/images/ys.png",
        "http://news.nankai.edu.cn/images/yangshipin1.png",
        "http://news.nankai.edu.cn/images/jiaoyu.png",
        "http://news.nankai.edu.cn/images/jybewm.png",
        "http://news.nankai.edu.cn/images/toutiao.png",
        "http://news.nankai.edu.cn/images/toutiaohao1.png",
        "http://news.nankai.edu.cn/ywsd/images/list_04.jpg",
        "http://news.nankai.edu.cn/ywsd/images/list_12.jpg",
        "http://news.nankai.edu.cn/pic/003/000/241/00300024169_6a089d05.jpg",
        "http://news.nankai.edu.cn/ywsd/images/list_21.jpg"
    ],
    "links": [
        "http://news.nankai.edu.cn/index.shtml",
        "http://news.nankai.edu.cn/ywsd/index.shtml",
        "http://news.nankai.edu.cn/mtnk/index.shtml",
        "http://news.nankai.edu.cn/gynk/index.shtml",
        "http://news.nankai.edu.cn/nkrw/index.shtml",
        "http://news.nankai.edu.cn/nkdxb/index.shtml",
        "http://news.nankai.edu.cn/sp/index.shtml",
        "http://news.nankai.edu.cn/gb/index.shtml",
        "http://news.nankai.edu.cn/index.shtml",
        "http://news.nankai.edu.cn/zhxw/index.shtml",
        "http://news.nankai.edu.cn/wx/system/2019/06/03/030033750.shtml",
        "http://news.nankai.edu.cn/wx/system/2019/06/03/030033750.shtml",
        "http://news.nankai.edu.cn/wx/index.shtml",
        "http://news.nankai.edu.cn/ywsd/system/2024/12/03/030064867.shtml",
        "http://news.nankai.edu.cn/ywsd/system/2024/12/05/030064916.shtml",
        "http://news.nankai.edu.cn/ywsd/system/2024/12/05/030064905.shtml",
        "http://news.nankai.edu.cn/ywsd/system/2024/12/04/030064892.shtml",
        "http://news.nankai.edu.cn/ywsd/system/2024/12/05/030064917.shtml",
        "http://news.nankai.edu.cn/ywsd/system/2024/12/03/030064855.shtml",
        "http://news.nankai.edu.cn/ywsd/system/2024/12/05/030064914.shtml",
        "http://news.nankai.edu.cn/ywsd/system/2024/12/05/030064912.shtml",
        "http://news.nankai.edu.cn/ywsd/system/2024/12/04/030064885.shtml",
        "http://news.nankai.edu.cn/ywsd/system/2024/12/03/030064868.shtml"
    ],
    "publisher": "未知",
    "source": "南开大学新闻网",
    "views": null,
    "attachments": [],
    "contact_info": {
        "email": "nknews@nankai.edu.cn"
    }
}