{
    "title": "【组图】天开园，日新月异，未来可期！-南开要闻-南开大学",
    "url": "https://news.nankai.edu.cn/ywsd/system/2023/07/18/030057138.shtml",
    "publish_time": "2023-07-18",
    "content": "首页\n南开要闻\n媒体南开\n南开校史\n光影南开\n南开故事\n南开大学报\n视频\n广播\n您当前的位置 ：\n南开大学\n>>\n南开要闻\n【组图】天开园，日新月异，未来可期！\n发稿 13:58\n文字/乔仁铭 周海浪 卢宇佳\n摄影/卢宇佳 宗琪琪 乔仁铭 李文洋 朱俊玮 李硕\n今年5月18日，渤海之滨，“石破天开”──天津市深入贯彻落实党的二十大精神，全力打造的天开高教科创园盛大开园。科创服务资源在这里汇聚，创新创业热潮在这里奔涌，南开大学入驻区里一片欣欣向荣的景象。\n开园近两个月时间里，南开师生校友纷纷走进天开园，了解政策、感受环境、研学交流、参与创新创业大赛等各类精彩活动……在越来越多南开人的关注参与下，这里的科创氛围持续高涨！天开园，日新月异，未来可期！\n天开高教科创园主雕塑在核心先导区竖立，莫比乌斯环围合“母育子”的形象寓意着“天开”的未来拥有无限可能。\n南开大学校长陈雨露与师生代表一起参观南开大学创新创业教育成果互动体验展示专区。专区展示了科技含量高、互动展示性强的双创项目成果及精品科普活动。\n入驻天开园的企业代表从天津南开大学资产经营有限责任公司负责人手中拿到了“新家”钥匙，正式踏入这片承载着热切期望的梦想之地。\n天津南开大学资产经营有限责任公司教职工积极对接入驻企业代表，认真做好各项服务保障工作，为师生校友创新创业营造良好环境氛围。\n南开大学入驻企业代表在天开园综合服务中心办理相关手续。综合服务中心开设的窗口，涵盖企业开办、企业纳税等相关业务。\n南开大学师生代表在天开园综合服务中心参观，认真了解政务服务等各类信息。\n天开园综合服务中心工作人员向南开学子发放各类业务办理宣传单。\n南开学子认真学习了解入驻园区的政策信息。\n天开园综合服务中心工作人员为南开学子创新创业项目答疑解惑、指点迷津。\n天开园工作人员认真讲解园区发展建设情况。\n南开大学在天开园举办学生创新创业路演等各类缤纷多彩活动。\n南开大学学生创新创业项目代表从多维度进行路演展示，与评审专家进行深入交流。\n南开学子认真聆听路演项目介绍。\n南开学子认真聆听路演项目介绍。\n天开园南开大学入驻区企业办公现场\n天开园南开大学入驻区企业办公现场\n天开园南开大学入驻区企业办公现场\n南开师生代表参观天开园南开大学入驻区\n南开师生校友在天开园南开大学入驻区交流讨论\n南开师生校友在天开园南开大学入驻区交流讨论\n编辑：\n闫瑾\n微信往期推送\n更多...\n西南联合研究生院博士生学术...\n南开大学召开智库建设重点工...\n重磅签约！南开大学第一附属...\n缅怀大师！南开大学首颁数学...\n我校牵头国家自然科学基金重...\n2024数字创意驱动城市高质量...\n南开数项智库成果获评CTTI智...\n“超越传统的电池体系”重大...\n先进能源材料化学教育部重点...\neScience卓越讲座和研究生线...\n新闻热线：022-23508464 022-85358737\n投稿信箱：\n本网站由南开大学新闻中心设计维护\nCopyright@2014 津ICP备12003308号-1\n南开大学\n校史网\n版权声明：本网站由南开大学版权所有，如转载本网站内容，请注明出处。",
    "images": [
        "http://news.nankai.edu.cn/images/i_weixin.png",
        "http://news.nankai.edu.cn/images/weixin.jpg",
        "http://news.nankai.edu.cn/images/i_weibo.png",
        "http://news.nankai.edu.cn/images/weibo.jpg",
        "http://news.nankai.edu.cn/images/i_douyin.png",
        "http://news.nankai.edu.cn/images/dy11.png",
        "http://news.nankai.edu.cn/images/i_blibili.png",
        "http://news.nankai.edu.cn/images/bz.png",
        "http://news.nankai.edu.cn/images/kuaishou.png",
        "http://news.nankai.edu.cn/images/kuaishou1.png",
        "http://news.nankai.edu.cn/images/xxqg.png",
        "http://news.nankai.edu.cn/images/xxqgewm.png",
        "http://news.nankai.edu.cn/images/ys.png",
        "http://news.nankai.edu.cn/images/yangshipin1.png",
        "http://news.nankai.edu.cn/images/jiaoyu.png",
        "http://news.nankai.edu.cn/images/jybewm.png",
        "http://news.nankai.edu.cn/images/toutiao.png",
        "http://news.nankai.edu.cn/images/toutiaohao1.png",
        "http://news.nankai.edu.cn/pic/003/000/547/00300054752_0a83f993.jpg",
        "http://news.nankai.edu.cn/pic/003/000/547/00300054753_a749403a.jpg",
        "http://news.nankai.edu.cn/pic/003/000/547/00300054754_f3f984e1.jpg",
        "http://news.nankai.edu.cn/pic/003/000/547/00300054755_cb6a0f89.jpg",
        "http://news.nankai.edu.cn/pic/003/000/547/00300054756_5c795a63.jpg",
        "http://news.nankai.edu.cn/pic/003/000/547/00300054757_6dfddfae.jpg",
        "http://news.nankai.edu.cn/pic/003/000/547/00300054758_ef73654b.jpg",
        "http://news.nankai.edu.cn/pic/003/000/547/00300054759_523e03fc.jpg",
        "http://news.nankai.edu.cn/pic/003/000/547/00300054760_36048d41.jpg",
        "http://news.nankai.edu.cn/pic/003/000/547/00300054762_c8eaf4ab.jpg",
        "http://news.nankai.edu.cn/pic/003/000/547/00300054765_6e675290.jpg",
        "http://news.nankai.edu.cn/pic/003/000/547/00300054767_0209f7f4.jpg",
        "http://news.nankai.edu.cn/pic/003/000/547/00300054768_88b55d50.jpg",
        "http://news.nankai.edu.cn/pic/003/000/547/00300054769_579bf6fd.jpg",
        "http://news.nankai.edu.cn/pic/003/000/547/00300054772_33ce466e.jpg",
        "http://news.nankai.edu.cn/pic/003/000/547/00300054774_7184f489.jpg",
        "http://news.nankai.edu.cn/pic/003/000/547/00300054775_001e71c7.jpg",
        "http://news.nankai.edu.cn/pic/003/000/547/00300054776_396ed7bb.jpg",
        "http://news.nankai.edu.cn/pic/003/000/547/00300054777_75fd28cd.jpg",
        "http://news.nankai.edu.cn/pic/003/000/547/00300054778_8bab80f6.jpg",
        "http://news.nankai.edu.cn/ywsd/images/list_04.jpg",
        "http://news.nankai.edu.cn/ywsd/images/list_12.jpg",
        "http://news.nankai.edu.cn/pic/003/000/241/00300024169_6a089d05.jpg",
        "http://news.nankai.edu.cn/ywsd/images/list_21.jpg"
    ],
    "links": [
        "http://news.nankai.edu.cn/index.shtml",
        "http://news.nankai.edu.cn/ywsd/index.shtml",
        "http://news.nankai.edu.cn/mtnk/index.shtml",
        "http://news.nankai.edu.cn/gynk/index.shtml",
        "http://news.nankai.edu.cn/nkrw/index.shtml",
        "http://news.nankai.edu.cn/nkdxb/index.shtml",
        "http://news.nankai.edu.cn/sp/index.shtml",
        "http://news.nankai.edu.cn/gb/index.shtml",
        "http://news.nankai.edu.cn/index.shtml",
        "http://news.nankai.edu.cn/ywsd/index.shtml",
        "http://news.nankai.edu.cn/wx/system/2019/06/03/030033750.shtml",
        "http://news.nankai.edu.cn/wx/system/2019/06/03/030033750.shtml",
        "http://news.nankai.edu.cn/wx/index.shtml",
        "http://news.nankai.edu.cn/ywsd/system/2024/12/03/030064867.shtml",
        "http://news.nankai.edu.cn/ywsd/system/2024/12/05/030064916.shtml",
        "http://news.nankai.edu.cn/ywsd/system/2024/12/05/030064905.shtml",
        "http://news.nankai.edu.cn/ywsd/system/2024/12/04/030064892.shtml",
        "http://news.nankai.edu.cn/ywsd/system/2024/12/05/030064917.shtml",
        "http://news.nankai.edu.cn/ywsd/system/2024/12/03/030064855.shtml",
        "http://news.nankai.edu.cn/ywsd/system/2024/12/05/030064914.shtml",
        "http://news.nankai.edu.cn/ywsd/system/2024/12/05/030064912.shtml",
        "http://news.nankai.edu.cn/ywsd/system/2024/12/04/030064885.shtml",
        "http://news.nankai.edu.cn/ywsd/system/2024/12/03/030064868.shtml"
    ],
    "publisher": "未知",
    "source": "南开大学新闻网",
    "views": null,
    "attachments": [],
    "contact_info": {
        "email": "nknews@nankai.edu.cn"
    }
}