{
    "title": "侯欣一：税收一定要法律管-南开之声-南开大学",
    "url": "https://news.nankai.edu.cn/nkzs/system/2015/03/11/000224715.shtml",
    "publish_time": "2015-03-11",
    "content": "首页\n南开要闻\n媒体南开\n南开校史\n光影南开\n南开故事\n南开大学报\n视频\n广播\n您当前的位置 ：\n南开大学\n>>\n南开之声\n侯欣一：税收一定要法律管\n发稿 15:17\n本报北京3月10日电(记者 罗娟)“比较草案第二稿，把税率拿掉后，还是不是‘税收法定’原则？”3月9日上午，政协社科界讨论立法法修正案草案，当全国政协委员、中国律师协会副会长朱征夫抛出这一问题时，在场的多家媒体立刻围拢上来。\n3月8日，十二届全国人大三次会议听取全国人大关于立法法修正案草案的说明，这是该法实施15年来第一次修改，其中最受老百姓关注的是“税收法定原则”。\n在立法法修正案草案中，去年提交全国人大常委会审议的二审稿第八条中的“税种、纳税人、征税对象、计税依据、税率和税收征收管理等税收基本制度”被改为了“税种的开征、停征和税收征收管理的基本制度”要制定法律。\n讨论现场，南开大学法学院副院长侯欣一委员认为，这样做有可能被误会是删除了“税收法定原则”。“税收一定要法律管。”他认为，虽然1985年全国人大授权国务院税收调整权，但事隔20年，税率税种发生了很大变化，“去年成品油消费税3连涨，社会反响大。”\n对此，全国人大常委会法制工作委员会副主任委员阚珂解释，实际上并不是删除“税收法定原则”，税种就包括了纳税人、征税对象、计税依据和税率。\n“是‘老子’和‘儿子’的关系，原来的写法把‘老子’和‘儿子’写到一起了。”阚珂进一步说，“老子”是指现有修正案草案里的税种，“儿子”则是删除的税率等基本概念。\n“那税率的调整权还是在全国人大吗？”面对记者的提问，阚珂做出了肯定的回答：“十八届三中全会公告明确，落实税收法定原则。单独把税率授给政府，这是不可能的。”\n为何大家如此关注“税收法定原则”？全国人大代表、北京律师协会会长李大进直言，因为“税收和每个人都有关系”。他把立法法修订比作建造一栋品质高的房子，“大家都想住进设计合理、舒适卫生、生活方便、没有垃圾的房子，立法法就是给你修好房子的。”\n作者：罗娟  原标题：“税收法定原则”最受百姓关注\n编辑：\n赖鸿杰\n微信往期推送\n更多...\n西南联合研究生院博士生学术...\n南开大学召开智库建设重点工...\n重磅签约！南开大学第一附属...\n缅怀大师！南开大学首颁数学...\n我校牵头国家自然科学基金重...\n2024数字创意驱动城市高质量...\n南开数项智库成果获评CTTI智...\n“超越传统的电池体系”重大...\n先进能源材料化学教育部重点...\neScience卓越讲座和研究生线...\n新闻热线：022-23508464 022-85358737\n投稿信箱：\n本网站由南开大学新闻中心设计维护\nCopyright@2014 津ICP备12003308号-1\n南开大学\n校史网\n版权声明：本网站由南开大学版权所有，如转载本网站内容，请注明出处。",
    "images": [
        "http://news.nankai.edu.cn/images/i_weixin.png",
        "http://news.nankai.edu.cn/images/weixin.jpg",
        "http://news.nankai.edu.cn/images/i_weibo.png",
        "http://news.nankai.edu.cn/images/weibo.jpg",
        "http://news.nankai.edu.cn/images/i_douyin.png",
        "http://news.nankai.edu.cn/images/dy11.png",
        "http://news.nankai.edu.cn/images/i_blibili.png",
        "http://news.nankai.edu.cn/images/bz.png",
        "http://news.nankai.edu.cn/images/kuaishou.png",
        "http://news.nankai.edu.cn/images/kuaishou1.png",
        "http://news.nankai.edu.cn/images/xxqg.png",
        "http://news.nankai.edu.cn/images/xxqgewm.png",
        "http://news.nankai.edu.cn/images/ys.png",
        "http://news.nankai.edu.cn/images/yangshipin1.png",
        "http://news.nankai.edu.cn/images/jiaoyu.png",
        "http://news.nankai.edu.cn/images/jybewm.png",
        "http://news.nankai.edu.cn/images/toutiao.png",
        "http://news.nankai.edu.cn/images/toutiaohao1.png",
        "http://news.nankai.edu.cn/ywsd/images/list_04.jpg",
        "http://news.nankai.edu.cn/ywsd/images/list_12.jpg",
        "http://news.nankai.edu.cn/pic/003/000/241/00300024169_6a089d05.jpg",
        "http://news.nankai.edu.cn/ywsd/images/list_21.jpg"
    ],
    "links": [
        "http://news.nankai.edu.cn/index.shtml",
        "http://news.nankai.edu.cn/ywsd/index.shtml",
        "http://news.nankai.edu.cn/mtnk/index.shtml",
        "http://news.nankai.edu.cn/gynk/index.shtml",
        "http://news.nankai.edu.cn/nkrw/index.shtml",
        "http://news.nankai.edu.cn/nkdxb/index.shtml",
        "http://news.nankai.edu.cn/sp/index.shtml",
        "http://news.nankai.edu.cn/gb/index.shtml",
        "http://news.nankai.edu.cn/index.shtml",
        "http://news.nankai.edu.cn/nkzs/index.shtml",
        "http://news.nankai.edu.cn/wx/system/2019/06/03/030033750.shtml",
        "http://news.nankai.edu.cn/wx/system/2019/06/03/030033750.shtml",
        "http://news.nankai.edu.cn/wx/index.shtml",
        "http://news.nankai.edu.cn/ywsd/system/2024/12/03/030064867.shtml",
        "http://news.nankai.edu.cn/ywsd/system/2024/12/05/030064916.shtml",
        "http://news.nankai.edu.cn/ywsd/system/2024/12/05/030064905.shtml",
        "http://news.nankai.edu.cn/ywsd/system/2024/12/04/030064892.shtml",
        "http://news.nankai.edu.cn/ywsd/system/2024/12/05/030064917.shtml",
        "http://news.nankai.edu.cn/ywsd/system/2024/12/03/030064855.shtml",
        "http://news.nankai.edu.cn/ywsd/system/2024/12/05/030064914.shtml",
        "http://news.nankai.edu.cn/ywsd/system/2024/12/05/030064912.shtml",
        "http://news.nankai.edu.cn/ywsd/system/2024/12/04/030064885.shtml",
        "http://news.nankai.edu.cn/ywsd/system/2024/12/03/030064868.shtml"
    ],
    "publisher": "未知",
    "source": "工人日报 2015年3月11日3版",
    "views": null,
    "attachments": [],
    "contact_info": {
        "email": "nknews@nankai.edu.cn"
    }
}