{
    "title": "信息学院“同学少年·梦想中国”暑期实践队启航-综合新闻-南开大学",
    "url": "https://news.nankai.edu.cn/zhxw/system/2013/07/27/000135795.shtml",
    "publish_time": "2013-07-27",
    "content": "首页\n南开要闻\n媒体南开\n南开校史\n光影南开\n南开故事\n南开大学报\n视频\n广播\n您当前的位置 ：\n南开大学\n>>\n综合新闻\n信息学院“同学少年·梦想中国”暑期实践队启航\n发稿 11:46\n南开新闻网讯\n(通讯员 韩旭 宋彤彤 王莉)7月23日，南开大学赴湖南“重温青春力量”暑期社会实践队踏上了“同学少年·梦想中国”的韶山之旅。\n此次社会实践以“寻梦”为主题，一方面积极探索革命先辈青年时期的寻梦历程，另一方面响应习近平总书记“一定要把毛主席故居办成爱国主义和革命传统教育基地，特别是在对青少年一代教育中发挥更大作用”的号召，旨在通过对主席“恰同学少年梦”的学习和感悟，铸就属于青年学子自己的中国梦。\n这是实践队开展活动的第一天。队员们首先来到了韶山毛泽东同志纪念馆，参观了展示的毛主席遗物，认真观看和学习了毛主席的生平故事，对毛主席的学习和生活有了更深的认识，深刻感受到了主席一生的勤俭节约和无私为公的品质。在参观过程中，实践队长许傲同学还为实践队员和参观游客做了有关毛主席生平事迹的义务讲解。之后队员们又前往了毛泽东同志故居，走进毛主席生活的地方，感悟伟人生活和成长的足迹，进一步了解了毛泽东思想的起源。随后实践队员又来了毛泽东同志铜像广场，在烈日下感受伟人的光辉历史，向主席鞠躬致敬。\n实践队队员高健同学说：“在主席像前，我更深刻的感受到了对毛主席‘一心为公，勤勤恳恳’精神的敬佩，激发了我强烈的爱国热情，也让我对‘中国梦’、‘青年梦’的含义有了新的把握。我希望自己怀着‘一心为公’的热情，以毛主席为榜样，秉承南开‘公能’校训，努力学习科学文化知识，积极参加利国利民的公益活动，锻炼综合能力，去影响和感染更多的人，用一颗“奉献之心”回报社会，为中华民族的伟大复兴贡献我们青年学子的一份力量。”\n编辑：\n张剑\n微信往期推送\n更多...\n西南联合研究生院博士生学术...\n南开大学召开智库建设重点工...\n重磅签约！南开大学第一附属...\n缅怀大师！南开大学首颁数学...\n我校牵头国家自然科学基金重...\n2024数字创意驱动城市高质量...\n南开数项智库成果获评CTTI智...\n“超越传统的电池体系”重大...\n先进能源材料化学教育部重点...\neScience卓越讲座和研究生线...\n新闻热线：022-23508464 022-85358737\n投稿信箱：\n本网站由南开大学新闻中心设计维护\nCopyright@2014 津ICP备12003308号-1\n南开大学\n校史网\n版权声明：本网站由南开大学版权所有，如转载本网站内容，请注明出处。",
    "images": [
        "http://news.nankai.edu.cn/images/i_weixin.png",
        "http://news.nankai.edu.cn/images/weixin.jpg",
        "http://news.nankai.edu.cn/images/i_weibo.png",
        "http://news.nankai.edu.cn/images/weibo.jpg",
        "http://news.nankai.edu.cn/images/i_douyin.png",
        "http://news.nankai.edu.cn/images/dy11.png",
        "http://news.nankai.edu.cn/images/i_blibili.png",
        "http://news.nankai.edu.cn/images/bz.png",
        "http://news.nankai.edu.cn/images/kuaishou.png",
        "http://news.nankai.edu.cn/images/kuaishou1.png",
        "http://news.nankai.edu.cn/images/xxqg.png",
        "http://news.nankai.edu.cn/images/xxqgewm.png",
        "http://news.nankai.edu.cn/images/ys.png",
        "http://news.nankai.edu.cn/images/yangshipin1.png",
        "http://news.nankai.edu.cn/images/jiaoyu.png",
        "http://news.nankai.edu.cn/images/jybewm.png",
        "http://news.nankai.edu.cn/images/toutiao.png",
        "http://news.nankai.edu.cn/images/toutiaohao1.png",
        "http://news.nankai.edu.cn/ywsd/images/list_04.jpg",
        "http://news.nankai.edu.cn/ywsd/images/list_12.jpg",
        "http://news.nankai.edu.cn/pic/003/000/241/00300024169_6a089d05.jpg",
        "http://news.nankai.edu.cn/ywsd/images/list_21.jpg"
    ],
    "links": [
        "http://news.nankai.edu.cn/index.shtml",
        "http://news.nankai.edu.cn/ywsd/index.shtml",
        "http://news.nankai.edu.cn/mtnk/index.shtml",
        "http://news.nankai.edu.cn/gynk/index.shtml",
        "http://news.nankai.edu.cn/nkrw/index.shtml",
        "http://news.nankai.edu.cn/nkdxb/index.shtml",
        "http://news.nankai.edu.cn/sp/index.shtml",
        "http://news.nankai.edu.cn/gb/index.shtml",
        "http://news.nankai.edu.cn/index.shtml",
        "http://news.nankai.edu.cn/zhxw/index.shtml",
        "http://news.nankai.edu.cn/wx/system/2019/06/03/030033750.shtml",
        "http://news.nankai.edu.cn/wx/system/2019/06/03/030033750.shtml",
        "http://news.nankai.edu.cn/wx/index.shtml",
        "http://news.nankai.edu.cn/ywsd/system/2024/12/03/030064867.shtml",
        "http://news.nankai.edu.cn/ywsd/system/2024/12/05/030064916.shtml",
        "http://news.nankai.edu.cn/ywsd/system/2024/12/05/030064905.shtml",
        "http://news.nankai.edu.cn/ywsd/system/2024/12/04/030064892.shtml",
        "http://news.nankai.edu.cn/ywsd/system/2024/12/05/030064917.shtml",
        "http://news.nankai.edu.cn/ywsd/system/2024/12/03/030064855.shtml",
        "http://news.nankai.edu.cn/ywsd/system/2024/12/05/030064914.shtml",
        "http://news.nankai.edu.cn/ywsd/system/2024/12/05/030064912.shtml",
        "http://news.nankai.edu.cn/ywsd/system/2024/12/04/030064885.shtml",
        "http://news.nankai.edu.cn/ywsd/system/2024/12/03/030064868.shtml"
    ],
    "publisher": "未知",
    "source": "南开新闻网",
    "views": null,
    "attachments": [],
    "contact_info": {
        "email": "nknews@nankai.edu.cn"
    }
}