{
    "title": "法学院、药学院开展本科教学工作审核评估自评-南开要闻-南开大学",
    "url": "https://news.nankai.edu.cn/ywsd/system/2014/10/16/000204954.shtml",
    "publish_time": "2014-10-16",
    "content": "首页\n南开要闻\n媒体南开\n南开校史\n光影南开\n南开故事\n南开大学报\n视频\n广播\n您当前的位置 ：\n南开大学\n>>\n南开要闻\n法学院、药学院开展本科教学工作审核评估自评\n发稿 14:25\n南开新闻网讯\n(记者 张轶帆 实习记者 郝静秋摄影任永华张轶帆)10月15日，法学院、药学院分别举行本科教学工作审核评估自评会。校内学院审核评估专家组对两学院的本科教学工作进行审核评估。\n法学院、药学院有关负责人分别向专家组汇报了近年来本科教学工作情况。\n药学院的前身为南开大学化学学院药学系，2007年3月15日药学院正式成立。目前，药学院有1个药学本科专业，15个科研实验室，1个药学实验教学中心，有药物化学、微生物与生化药学、生药学等3个二级学科。2009年成立天津市分子药物研究重点实验室，2010年获得制药工程硕士专业学位授予权，2011年获得药学一级学科硕士学位授予权。2011年成为药物化学生物学国家重点实验室(建)依托单位之一。目前，药学院通过与生命科学学院和化学学院合作，招收攻读微生物学和化学生物学专业的博士学位研究生。\n在成立伊始，药学院就确定了明确的办学目标，即“有特色、高水平、国内外知名”。学院的办学原则是通过教学、科研相结合的教育模式，培养面向国内、国际一流高等学府和研究机构，服务社会的合格的毕业生。目前，药学院以药学专业为主，在药物化学、药剂学、药理学、天然药物学和药物分析学等几方面均得到了发展，毕业生越来越受到用人单位的认可。\n法学院根据教育规律、发展历史和社会需求形成了南开法学的特色办学，并以培养具有南开“公能”品格和国际视野的应用型、研究型、复合型卓越法律人才为目标。学院不断加强师资队伍建设，鼓励教师进行教学方法的改革。同时调整课程设置，建设教育实践基地，加大合作办学，发展第二课堂，为学生的实践教学与合作交流创造条件。\n法学院教学管理制度健全，能够严格执行学校各项规章制度，同时还根据自身学科特点，制定一批教学管理的规章制度。学院注重学生的指导与服务工作，鼓励并组织院内学生积极参与校内外各类学术文化活动，并充分调动各种资源，努力为广大毕业生拓宽就业渠道，学生对老师的水平和敬业精神总体上评价较高。\n自评汇报后，专家组在与师生进行座谈交流、考察学院的教学设施和办学条件、听取学院部分课程、查阅支撑材料后给出反馈意见。\n专家组对两学院在本科教学工作方面取得的成绩给予肯定，并在反馈意见中指出，建设高层次的师资队伍，扩大学生交流的机会与深度是法学院需要努力的方向，在发展传统优势学科的基础上，更应大力发展学科的特色教学，突出南开模式的人才培养。专家组建议药学院以此次评估为契机认真研究学院的专业建设、课程体系、人才引进、师德培养等工作，加强本科生实验教学，通过多种方式调动教师积极性，加大对教师教学的激励力度及本科教学经费投入，将学院办出水平，办出特色。\n据悉，2014-2018年国家启动新一轮评估为“审核评估”，我校是教育部选定的第一批受评学校。不同于上一轮的“水平评估”，“审核”是本轮评估的特点。突出以学校为主体，以学生发展为本；帮学校反思，为学校服务，替国家把关。表现为“三自四度”。“三自”即学校根据办学定位、培养目标和特点，自己定标尺，自己划刻度，用自己的标尺测量评价自己，突出办学的自主性和多样性。“四度”即围绕学校“办学定位和学生培养目标与学生发展、国家和区域经济社会发展需求的适应度，教师和教学资源的保障度，教学和质量保障体系运行的有效度，学生和社会用人单位的满意度”的“四度”主线重点审核。\n教育部审核评估专家组将于今年12月中旬进校，进行为期约4天的现场考察。有针对性地分别进行深度个别访谈、听课看课，内外实地考察、文卷审阅、问题诊断、沟通交流等，突出“核”字，核对学校的自评是否准确到位。评估结论以“值得肯定之处、需要改进之处、必须整改之处”写实性表述，不评分、不分等，淡化功利心态，强化内涵建设。\n编辑：\n赖鸿杰\n微信往期推送\n更多...\n西南联合研究生院博士生学术...\n南开大学召开智库建设重点工...\n重磅签约！南开大学第一附属...\n缅怀大师！南开大学首颁数学...\n我校牵头国家自然科学基金重...\n2024数字创意驱动城市高质量...\n南开数项智库成果获评CTTI智...\n“超越传统的电池体系”重大...\n先进能源材料化学教育部重点...\neScience卓越讲座和研究生线...\n新闻热线：022-23508464 022-85358737\n投稿信箱：\n本网站由南开大学新闻中心设计维护\nCopyright@2014 津ICP备12003308号-1\n南开大学\n校史网\n版权声明：本网站由南开大学版权所有，如转载本网站内容，请注明出处。",
    "images": [
        "http://news.nankai.edu.cn/images/i_weixin.png",
        "http://news.nankai.edu.cn/images/weixin.jpg",
        "http://news.nankai.edu.cn/images/i_weibo.png",
        "http://news.nankai.edu.cn/images/weibo.jpg",
        "http://news.nankai.edu.cn/images/i_douyin.png",
        "http://news.nankai.edu.cn/images/dy11.png",
        "http://news.nankai.edu.cn/images/i_blibili.png",
        "http://news.nankai.edu.cn/images/bz.png",
        "http://news.nankai.edu.cn/images/kuaishou.png",
        "http://news.nankai.edu.cn/images/kuaishou1.png",
        "http://news.nankai.edu.cn/images/xxqg.png",
        "http://news.nankai.edu.cn/images/xxqgewm.png",
        "http://news.nankai.edu.cn/images/ys.png",
        "http://news.nankai.edu.cn/images/yangshipin1.png",
        "http://news.nankai.edu.cn/images/jiaoyu.png",
        "http://news.nankai.edu.cn/images/jybewm.png",
        "http://news.nankai.edu.cn/images/toutiao.png",
        "http://news.nankai.edu.cn/images/toutiaohao1.png",
        "http://news.nankai.edu.cn/pic/0/00/14/55/145544_956643.jpg",
        "http://news.nankai.edu.cn/pic/0/00/14/55/145545_271789.jpg",
        "http://news.nankai.edu.cn/ywsd/images/list_04.jpg",
        "http://news.nankai.edu.cn/ywsd/images/list_12.jpg",
        "http://news.nankai.edu.cn/pic/003/000/241/00300024169_6a089d05.jpg",
        "http://news.nankai.edu.cn/ywsd/images/list_21.jpg"
    ],
    "links": [
        "http://news.nankai.edu.cn/index.shtml",
        "http://news.nankai.edu.cn/ywsd/index.shtml",
        "http://news.nankai.edu.cn/mtnk/index.shtml",
        "http://news.nankai.edu.cn/gynk/index.shtml",
        "http://news.nankai.edu.cn/nkrw/index.shtml",
        "http://news.nankai.edu.cn/nkdxb/index.shtml",
        "http://news.nankai.edu.cn/sp/index.shtml",
        "http://news.nankai.edu.cn/gb/index.shtml",
        "http://news.nankai.edu.cn/index.shtml",
        "http://news.nankai.edu.cn/ywsd/index.shtml",
        "http://news.nankai.edu.cn/wx/system/2019/06/03/030033750.shtml",
        "http://news.nankai.edu.cn/wx/system/2019/06/03/030033750.shtml",
        "http://news.nankai.edu.cn/wx/index.shtml",
        "http://news.nankai.edu.cn/ywsd/system/2024/12/03/030064867.shtml",
        "http://news.nankai.edu.cn/ywsd/system/2024/12/05/030064916.shtml",
        "http://news.nankai.edu.cn/ywsd/system/2024/12/05/030064905.shtml",
        "http://news.nankai.edu.cn/ywsd/system/2024/12/04/030064892.shtml",
        "http://news.nankai.edu.cn/ywsd/system/2024/12/05/030064917.shtml",
        "http://news.nankai.edu.cn/ywsd/system/2024/12/03/030064855.shtml",
        "http://news.nankai.edu.cn/ywsd/system/2024/12/05/030064914.shtml",
        "http://news.nankai.edu.cn/ywsd/system/2024/12/05/030064912.shtml",
        "http://news.nankai.edu.cn/ywsd/system/2024/12/04/030064885.shtml",
        "http://news.nankai.edu.cn/ywsd/system/2024/12/03/030064868.shtml"
    ],
    "publisher": "未知",
    "source": "南开新闻网",
    "views": null,
    "attachments": [],
    "contact_info": {
        "email": "nknews@nankai.edu.cn"
    }
}